valueeval24_hierocles_of_alexandria/__init__.py
valueeval24_hierocles_of_alexandria/__main__.py
valueeval24_hierocles_of_alexandria/multi_head_model.py
valueeval24_hierocles_of_alexandria/value_classifier.py
valueeval24_hierocles_of_alexandria-0.4.0.dist-info/METADATA
valueeval24_hierocles_of_alexandria-0.4.0.dist-info/WHEEL
valueeval24_hierocles_of_alexandria-0.4.0.dist-info/licenses/LICENSE
valueeval24_hierocles_of_alexandria-0.4.0.dist-info/RECORD
