Metadata-Version: 2.4
Name: valueeval24-hierocles-of-alexandria
Version: 0.4.0
Summary: Detect human values in text (winning model of ValueEval'24)
License: MIT License
License-File: LICENSE
Keywords: ai,artificial intelligence,classification,human values,schwartz values,vallueeval
Author: Sotirios Legkas
Maintainer: Johannes Kiesel
Maintainer-email: Johannes.Kiesel@gesis.org
Requires-Python: >=3.10,<3.14
Classifier: License :: Other/Proprietary License
Classifier: Programming Language :: Python :: 3
Classifier: Programming Language :: Python :: 3.10
Classifier: Programming Language :: Python :: 3.11
Classifier: Programming Language :: Python :: 3.12
Classifier: Programming Language :: Python :: 3.13
Requires-Dist: bitsandbytes (>=0.48.1,<0.49.0)
Requires-Dist: pandas (>=2.3.3,<3.0.0)
Requires-Dist: protobuf (>=5.29.1,<6.0.0)
Requires-Dist: sacremoses (>=0.1.1,<0.2.0)
Requires-Dist: torch (>=2.8.0,<3.0.0)
Requires-Dist: transformers[torch] (>=4.56.2,!=4.57.0,<5.0.0)
Project-URL: Issues, https://github.com/touche-webis-de/valueeval24-hierocles-of-alexandria/issues
Project-URL: Source, https://github.com/touche-webis-de/valueeval24-hierocles-of-alexandria
